# Comparing `tmp/pyc3dtools-0.2.3.win-amd64.zip` & `tmp/pyc3dtools-0.2.4.win-amd64.zip`

## zipinfo {}

```diff
@@ -1,17 +1,17 @@
-Zip file size: 10491 bytes, number of entries: 15
-drwxrwxrwx  2.0 fat        0 b- stor 23-May-18 19:25 Python311/
-drwxrwxrwx  2.0 fat        0 b- stor 23-May-18 19:25 Python311/Lib/
-drwxrwxrwx  2.0 fat        0 b- stor 23-May-18 19:25 Python311/Lib/site-packages/
-drwxrwxrwx  2.0 fat        0 b- stor 23-May-18 19:25 Python311/Lib/site-packages/pyc3dtools/
-drwxrwxrwx  2.0 fat        0 b- stor 23-May-18 19:25 Python311/Lib/site-packages/pyc3dtools-0.2.3-py3.11.egg-info/
-drwxrwxrwx  2.0 fat        0 b- stor 23-May-18 19:25 Python311/Lib/site-packages/pyc3dtools/__pycache__/
--rw-rw-rw-  2.0 fat     5638 b- defN 23-May-18 19:24 Python311/Lib/site-packages/pyc3dtools/pyc3dtools.py
+Zip file size: 11662 bytes, number of entries: 15
+drwxrwxrwx  2.0 fat        0 b- stor 23-May-28 17:28 Python311/
+drwxrwxrwx  2.0 fat        0 b- stor 23-May-28 17:28 Python311/Lib/
+drwxrwxrwx  2.0 fat        0 b- stor 23-May-28 17:28 Python311/Lib/site-packages/
+drwxrwxrwx  2.0 fat        0 b- stor 23-May-28 17:28 Python311/Lib/site-packages/pyc3dtools/
+drwxrwxrwx  2.0 fat        0 b- stor 23-May-28 17:28 Python311/Lib/site-packages/pyc3dtools-0.2.4-py3.11.egg-info/
+drwxrwxrwx  2.0 fat        0 b- stor 23-May-28 17:28 Python311/Lib/site-packages/pyc3dtools/__pycache__/
+-rw-rw-rw-  2.0 fat     6111 b- defN 23-May-28 17:17 Python311/Lib/site-packages/pyc3dtools/pyc3dtools.py
 -rw-rw-rw-  2.0 fat       88 b- defN 23-May-08 18:15 Python311/Lib/site-packages/pyc3dtools/__init__.py
--rw-rw-rw-  2.0 fat     9614 b- defN 23-May-18 19:25 Python311/Lib/site-packages/pyc3dtools/__pycache__/pyc3dtools.cpython-311.pyc
--rw-rw-rw-  2.0 fat      275 b- defN 23-May-18 19:25 Python311/Lib/site-packages/pyc3dtools/__pycache__/__init__.cpython-311.pyc
--rw-rw-rw-  2.0 fat        1 b- defN 23-May-18 19:25 Python311/Lib/site-packages/pyc3dtools-0.2.3-py3.11.egg-info/dependency_links.txt
--rw-rw-rw-  2.0 fat     7487 b- defN 23-May-18 19:25 Python311/Lib/site-packages/pyc3dtools-0.2.3-py3.11.egg-info/PKG-INFO
--rw-rw-rw-  2.0 fat       20 b- defN 23-May-18 19:25 Python311/Lib/site-packages/pyc3dtools-0.2.3-py3.11.egg-info/requires.txt
--rw-rw-rw-  2.0 fat      243 b- defN 23-May-18 19:25 Python311/Lib/site-packages/pyc3dtools-0.2.3-py3.11.egg-info/SOURCES.txt
--rw-rw-rw-  2.0 fat       11 b- defN 23-May-18 19:25 Python311/Lib/site-packages/pyc3dtools-0.2.3-py3.11.egg-info/top_level.txt
-15 files, 23377 bytes uncompressed, 7677 bytes compressed:  67.2%
+-rw-rw-rw-  2.0 fat    10565 b- defN 23-May-28 17:28 Python311/Lib/site-packages/pyc3dtools/__pycache__/pyc3dtools.cpython-311.pyc
+-rw-rw-rw-  2.0 fat      275 b- defN 23-May-28 17:28 Python311/Lib/site-packages/pyc3dtools/__pycache__/__init__.cpython-311.pyc
+-rw-rw-rw-  2.0 fat        1 b- defN 23-May-28 17:28 Python311/Lib/site-packages/pyc3dtools-0.2.4-py3.11.egg-info/dependency_links.txt
+-rw-rw-rw-  2.0 fat     9128 b- defN 23-May-28 17:28 Python311/Lib/site-packages/pyc3dtools-0.2.4-py3.11.egg-info/PKG-INFO
+-rw-rw-rw-  2.0 fat       20 b- defN 23-May-28 17:28 Python311/Lib/site-packages/pyc3dtools-0.2.4-py3.11.egg-info/requires.txt
+-rw-rw-rw-  2.0 fat      243 b- defN 23-May-28 17:28 Python311/Lib/site-packages/pyc3dtools-0.2.4-py3.11.egg-info/SOURCES.txt
+-rw-rw-rw-  2.0 fat       11 b- defN 23-May-28 17:28 Python311/Lib/site-packages/pyc3dtools-0.2.4-py3.11.egg-info/top_level.txt
+15 files, 26442 bytes uncompressed, 8848 bytes compressed:  66.5%
```

## zipnote {}

```diff
@@ -6,15 +6,15 @@
 
 Filename: Python311/Lib/site-packages/
 Comment: 
 
 Filename: Python311/Lib/site-packages/pyc3dtools/
 Comment: 
 
-Filename: Python311/Lib/site-packages/pyc3dtools-0.2.3-py3.11.egg-info/
+Filename: Python311/Lib/site-packages/pyc3dtools-0.2.4-py3.11.egg-info/
 Comment: 
 
 Filename: Python311/Lib/site-packages/pyc3dtools/__pycache__/
 Comment: 
 
 Filename: Python311/Lib/site-packages/pyc3dtools/pyc3dtools.py
 Comment: 
@@ -24,23 +24,23 @@
 
 Filename: Python311/Lib/site-packages/pyc3dtools/__pycache__/pyc3dtools.cpython-311.pyc
 Comment: 
 
 Filename: Python311/Lib/site-packages/pyc3dtools/__pycache__/__init__.cpython-311.pyc
 Comment: 
 
-Filename: Python311/Lib/site-packages/pyc3dtools-0.2.3-py3.11.egg-info/dependency_links.txt
+Filename: Python311/Lib/site-packages/pyc3dtools-0.2.4-py3.11.egg-info/dependency_links.txt
 Comment: 
 
-Filename: Python311/Lib/site-packages/pyc3dtools-0.2.3-py3.11.egg-info/PKG-INFO
+Filename: Python311/Lib/site-packages/pyc3dtools-0.2.4-py3.11.egg-info/PKG-INFO
 Comment: 
 
-Filename: Python311/Lib/site-packages/pyc3dtools-0.2.3-py3.11.egg-info/requires.txt
+Filename: Python311/Lib/site-packages/pyc3dtools-0.2.4-py3.11.egg-info/requires.txt
 Comment: 
 
-Filename: Python311/Lib/site-packages/pyc3dtools-0.2.3-py3.11.egg-info/SOURCES.txt
+Filename: Python311/Lib/site-packages/pyc3dtools-0.2.4-py3.11.egg-info/SOURCES.txt
 Comment: 
 
-Filename: Python311/Lib/site-packages/pyc3dtools-0.2.3-py3.11.egg-info/top_level.txt
+Filename: Python311/Lib/site-packages/pyc3dtools-0.2.4-py3.11.egg-info/top_level.txt
 Comment: 
 
 Zip file comment:
```

## Python311/Lib/site-packages/pyc3dtools/pyc3dtools.py

```diff
@@ -26,19 +26,17 @@
                 'Status' : 'Failed'
             })
     
         else:
             return GenerateOutput(result)
             
             
-    except:
-            return({
-                'error' : 'Failed'
-            })
-
+    except Exception as e:
+        return({'Status' : 'Failed',
+                'error' : e  })
     
 def getTRCMot(Token,file_path,des_path):          
     API_URL = "https://c3dtools.com/API/getOpenSimData"
     data = {'api_key':Token}  
     file_name = os.path.basename(file_path)
     file_size = os.stat(file_path).st_size
     with open(file_path, "rb") as f:
@@ -70,16 +68,17 @@
                 trcFile.writelines(result['trc']['h5'])
                 for d in result['trc']['data']:
                     trcFile.writelines(d)
                 trcFile.close()
 
             return GenerateOutput(result['c3d'])
       
-    except:
-        return({'Status' : 'Failed'  })
+    except Exception as e:
+        return({'Status' : 'Failed',
+                'error' : e  })
 
             
 
 
 
 def GenerateOutput(result):
     GP =  result["GP"]
@@ -132,15 +131,30 @@
 
    
     for f in Forceplates:
             f['Origin'] = f['orgin']     ## SORRY :)
             f['COP'] = np.array(f['COP'][:][:], dtype=object)
             f['GRF_VECTOR'] = np.array(f['GRF_VECTOR'][:][:], dtype=object)           
 
-            
+    
+    # convert all analog data to np array
+    Analog = np.array(Analog)
+    NewAnalog =[]
+    for f in Analog:
+        main_row = []
+        for j in range(int((len(f)/len(Analog_lbl)))-1):
+            row = []
+            for k in range(j*len(Analog_lbl),(j+1)*len(Analog_lbl)):
+                row.append(f[k])
+            main_row.append(row)
+
+        NewAnalog.append(main_row)    
+
+    Analog = NewAnalog
+
 
     return({
         'Status' : 'Success',
         'GP' : GP,
         'Markers' : Real_Markers,
         'Points' : Point,
         'Analog' : Analog,
```

## Python311/Lib/site-packages/pyc3dtools/__pycache__/pyc3dtools.cpython-311.pyc

### Python bytecode

```diff
@@ -1,10 +1,10 @@
 magic:    0xa70d0d0a
-moddate:  0x1f4a6664 (Thu May 18 15:54:07 2023 UTC)
-files sz: 5638
+moddate:  0x6b5b7364 (Sun May 28 13:47:23 2023 UTC)
+files sz: 6111
 code
    argcount  : 0
    nlocals   : 0
    stacksize : 2
    flags     : 0
    code
       0x9700640064016c005a00640064016c015a01640064016c025a03640064
@@ -45,31 +45,31 @@
                 54 STORE_NAME               7 (CallbackIOWrapper)
                 56 POP_TOP
    
      8          58 LOAD_CONST               4 (<code object readC3D, file "\Python311\Lib\site-packages\pyc3dtools\pyc3dtools.py", line 8>)
                 60 MAKE_FUNCTION            0
                 62 STORE_NAME               8 (readC3D)
    
-    39          64 LOAD_CONST               5 (<code object getTRCMot, file "\Python311\Lib\site-packages\pyc3dtools\pyc3dtools.py", line 39>)
+    37          64 LOAD_CONST               5 (<code object getTRCMot, file "\Python311\Lib\site-packages\pyc3dtools\pyc3dtools.py", line 37>)
                 66 MAKE_FUNCTION            0
                 68 STORE_NAME               9 (getTRCMot)
    
-    84          70 LOAD_CONST               6 (<code object GenerateOutput, file "\Python311\Lib\site-packages\pyc3dtools\pyc3dtools.py", line 84>)
+    83          70 LOAD_CONST               6 (<code object GenerateOutput, file "\Python311\Lib\site-packages\pyc3dtools\pyc3dtools.py", line 83>)
                 72 MAKE_FUNCTION            0
                 74 STORE_NAME              10 (GenerateOutput)
                 76 LOAD_CONST               1 (None)
                 78 RETURN_VALUE
    consts
       0
       None
       ('tqdm',)
       ('CallbackIOWrapper',)
       code
          argcount  : 2
-         nlocals   : 10
+         nlocals   : 11
          stacksize : 8
          flags     : 3
          code
             0x970064017d0264027c0069017d037401000000000000000000006a0100
             000000000000007c01a6010000ab0100000000000000006a020000000000
             0000007d047407000000000000000000007c016403a6020000ab02000000
             000000000035007d057409000000000000000000007c04640464056406ac
@@ -79,16 +79,17 @@
             097c076901ac0aa6030000ab0300000000000000007d08640064006400a6
             020000ab02000000000000000001006e0b23003100730477027803590077
             010100590001000100640064006400a6020000ab02000000000000000001
             006e0b230031007304770278035900770101005900010001000900741300
             0000000000000000006a0a00000000000000007c086a0b00000000000000
             00a6010000ab0100000000000000007d09640b7c097600720b7c09640b19
             000000000000000000640c640d9c0253007419000000000000000000007c
-            09a6010000ab010000000000000000530023000100640e640c6901630259
-            005300780359007701
+            09a6010000ab01000000000000000053002300741a000000000000000000
+            002400720f7d0a640c7c0a640e9c026302590064007d0a7e0a530064007d
+            0a7e0a77017700780359007701
            8           0 RESUME                   0
          
           10           2 LOAD_CONST               1 ('https://c3dtools.com/API/readC3D')
                        4 STORE_FAST               2 (API_URL)
          
           12           6 LOAD_CONST               2 ('api_key')
                        8 LOAD_FAST                0 (Token)
@@ -209,39 +210,56 @@
           30     >>  406 LOAD_GLOBAL             25 (NULL + GenerateOutput)
                      418 LOAD_FAST                9 (result)
                      420 PRECALL                  1
                      424 CALL                     1
                      434 RETURN_VALUE
                  >>  436 PUSH_EXC_INFO
          
-          33         438 POP_TOP
-         
-          35         440 LOAD_CONST              14 ('error')
-                     442 LOAD_CONST              12 ('Failed')
-         
-          34         444 BUILD_MAP                1
-                     446 SWAP                     2
-                     448 POP_EXCEPT
-                     450 RETURN_VALUE
-                 >>  452 COPY                     3
-                     454 POP_EXCEPT
-                     456 RERAISE                  1
+          33         438 LOAD_GLOBAL             26 (Exception)
+                     450 CHECK_EXC_MATCH
+                     452 POP_JUMP_FORWARD_IF_FALSE    15 (to 484)
+                     454 STORE_FAST              10 (e)
+         
+          34         456 LOAD_CONST              12 ('Failed')
+         
+          35         458 LOAD_FAST               10 (e)
+         
+          34         460 LOAD_CONST              14 (('Status', 'error'))
+                     462 BUILD_CONST_KEY_MAP      2
+                     464 SWAP                     2
+                     466 POP_EXCEPT
+                     468 LOAD_CONST               0 (None)
+                     470 STORE_FAST              10 (e)
+                     472 DELETE_FAST             10 (e)
+                     474 RETURN_VALUE
+                 >>  476 LOAD_CONST               0 (None)
+                     478 STORE_FAST              10 (e)
+                     480 DELETE_FAST             10 (e)
+                     482 RERAISE                  1
+         
+          33     >>  484 RERAISE                  0
+                 >>  486 COPY                     3
+                     488 POP_EXCEPT
+                     490 RERAISE                  1
          ExceptionTable:
            96 to 134 -> 302 [1] lasti
            136 to 230 -> 256 [2] lasti
            232 to 254 -> 302 [1] lasti
            256 to 262 -> 264 [4] lasti
            264 to 268 -> 302 [1] lasti
            270 to 270 -> 264 [4] lasti
            272 to 276 -> 302 [1] lasti
            302 to 308 -> 310 [3] lasti
            316 to 316 -> 310 [3] lasti
            326 to 402 -> 436 [0]
            406 to 432 -> 436 [0]
-           436 to 446 -> 452 [1] lasti
+           436 to 454 -> 486 [1] lasti
+           456 to 462 -> 476 [1] lasti
+           464 to 464 -> 486 [1] lasti
+           476 to 484 -> 486 [1] lasti
          consts
             None
             'https://c3dtools.com/API/readC3D'
             'api_key'
             'rb'
             'B'
             True
@@ -249,28 +267,28 @@
             ('total', 'unit', 'unit_scale', 'unit_divisor')
             'read'
             'upload_file'
             ('url', 'data', 'files')
             'error_msg'
             'Failed'
             ('error', 'Status')
-            'error'
-         names      ('os', 'stat', 'st_size', 'open', 'tqdm', 'CallbackIOWrapper', 'update', 'requests', 'post', 'json', 'loads', 'text', 'GenerateOutput')
-         varnames   ('Token', 'file_path', 'API_URL', 'data', 'file_size', 'f', 't', 'wrapped_file', 'resp', 'result')
+            ('Status', 'error')
+         names      ('os', 'stat', 'st_size', 'open', 'tqdm', 'CallbackIOWrapper', 'update', 'requests', 'post', 'json', 'loads', 'text', 'GenerateOutput', 'Exception')
+         varnames   ('Token', 'file_path', 'API_URL', 'data', 'file_size', 'f', 't', 'wrapped_file', 'resp', 'result', 'e')
          freevars   ()
          cellvars   ()
          filename   '\\Python311\\Lib\\site-packages\\pyc3dtools\\pyc3dtools.py'
          name       'readC3D'
          firstlineno 8
          lnotab
             0x0202040208033201220128012c0132fe2eff2e050201320108020e0102
-            fe06062003020204ff
+            fe060620031201020102ff18ff
       code
          argcount  : 3
-         nlocals   : 15
+         nlocals   : 16
          stacksize : 9
          flags     : 3
          code
             0x970064017d0364027c0069017d047400000000000000000000006a0100
             00000000000000a00200000000000000000000000000000000000000007c
             01a6010000ab0100000000000000007d057401000000000000000000006a
             0300000000000000007c01a6010000ab0100000000000000006a04000000
@@ -311,83 +329,85 @@
             00000000000000000000000000000000007c0b6415190000000000000000
             00641819000000000000000000a6010000ab01000000000000000001007c
             0b64151900000000000000000064141900000000000000000044005d177d
             0d7c0ea00e00000000000000000000000000000000000000007c0da60100
             00ab01000000000000000001008c187c0ea00f0000000000000000000000
             000000000000000000a6000000ab00000000000000000001007421000000
             000000000000007c0b641919000000000000000000a6010000ab01000000
-            0000000000530023000100641a640c6901630259005300780359007701
-          39           0 RESUME                   0
+            0000000000530023007422000000000000000000002400720f7d0f640c7c
+            0f641a9c026302590064007d0f7e0f530064007d0f7e0f77017700780359
+            007701
+          37           0 RESUME                   0
          
-          40           2 LOAD_CONST               1 ('https://c3dtools.com/API/getOpenSimData')
+          38           2 LOAD_CONST               1 ('https://c3dtools.com/API/getOpenSimData')
                        4 STORE_FAST               3 (API_URL)
          
-          41           6 LOAD_CONST               2 ('api_key')
+          39           6 LOAD_CONST               2 ('api_key')
                        8 LOAD_FAST                0 (Token)
                       10 BUILD_MAP                1
                       12 STORE_FAST               4 (data)
          
-          42          14 LOAD_GLOBAL              0 (os)
+          40          14 LOAD_GLOBAL              0 (os)
                       26 LOAD_ATTR                1 (path)
                       36 LOAD_METHOD              2 (basename)
                       58 LOAD_FAST                1 (file_path)
                       60 PRECALL                  1
                       64 CALL                     1
                       74 STORE_FAST               5 (file_name)
          
-          43          76 LOAD_GLOBAL              1 (NULL + os)
+          41          76 LOAD_GLOBAL              1 (NULL + os)
                       88 LOAD_ATTR                3 (stat)
                       98 LOAD_FAST                1 (file_path)
                      100 PRECALL                  1
                      104 CALL                     1
                      114 LOAD_ATTR                4 (st_size)
                      124 STORE_FAST               6 (file_size)
          
-          44         126 LOAD_GLOBAL             11 (NULL + open)
+          42         126 LOAD_GLOBAL             11 (NULL + open)
                      138 LOAD_FAST                1 (file_path)
                      140 LOAD_CONST               3 ('rb')
                      142 PRECALL                  2
                      146 CALL                     2
                      156 BEFORE_WITH
                      158 STORE_FAST               7 (f)
          
-          45         160 LOAD_GLOBAL             13 (NULL + tqdm)
+          43         160 LOAD_GLOBAL             13 (NULL + tqdm)
                      172 LOAD_FAST                6 (file_size)
                      174 LOAD_CONST               4 ('B')
                      176 LOAD_CONST               5 (True)
                      178 LOAD_CONST               6 (1024)
                      180 KW_NAMES                 7
                      182 PRECALL                  4
                      186 CALL                     4
                      196 BEFORE_WITH
                      198 STORE_FAST               8 (t)
          
-          46         200 LOAD_GLOBAL             15 (NULL + CallbackIOWrapper)
+          44         200 LOAD_GLOBAL             15 (NULL + CallbackIOWrapper)
                      212 LOAD_FAST                8 (t)
                      214 LOAD_ATTR                8 (update)
                      224 LOAD_FAST                7 (f)
                      226 LOAD_CONST               8 ('read')
                      228 PRECALL                  3
                      232 CALL                     3
                      242 STORE_FAST               9 (wrapped_file)
          
-          47         244 LOAD_GLOBAL             19 (NULL + requests)
+          45         244 LOAD_GLOBAL             19 (NULL + requests)
                      256 LOAD_ATTR               10 (post)
                      266 LOAD_FAST                3 (API_URL)
                      268 LOAD_CONST               5 (True)
                      270 LOAD_FAST                4 (data)
                      272 LOAD_CONST               9 ('upload_file')
                      274 LOAD_FAST                9 (wrapped_file)
                      276 BUILD_MAP                1
                      278 KW_NAMES                10
                      280 PRECALL                  4
                      284 CALL                     4
                      294 STORE_FAST              10 (resp)
          
-          45         296 LOAD_CONST               0 (None)
+          43         296 LOAD_CONST               0 (None)
                      298 LOAD_CONST               0 (None)
                      300 LOAD_CONST               0 (None)
                      302 PRECALL                  2
                      306 CALL                     2
                      316 POP_TOP
                      318 JUMP_FORWARD            11 (to 342)
                  >>  320 PUSH_EXC_INFO
@@ -398,15 +418,15 @@
                      330 POP_EXCEPT
                      332 RERAISE                  1
                  >>  334 POP_TOP
                      336 POP_EXCEPT
                      338 POP_TOP
                      340 POP_TOP
          
-          44     >>  342 LOAD_CONST               0 (None)
+          42     >>  342 LOAD_CONST               0 (None)
                      344 LOAD_CONST               0 (None)
                      346 LOAD_CONST               0 (None)
                      348 PRECALL                  2
                      352 CALL                     2
                      362 POP_TOP
                      364 JUMP_FORWARD            11 (to 388)
                  >>  366 PUSH_EXC_INFO
@@ -417,43 +437,43 @@
                      376 POP_EXCEPT
                      378 RERAISE                  1
                  >>  380 POP_TOP
                      382 POP_EXCEPT
                      384 POP_TOP
                      386 POP_TOP
          
-          49     >>  388 NOP
+          47     >>  388 NOP
          
-          50         390 LOAD_GLOBAL             23 (NULL + json)
+          48         390 LOAD_GLOBAL             23 (NULL + json)
                      402 LOAD_ATTR               12 (loads)
                      412 LOAD_FAST               10 (resp)
                      414 LOAD_ATTR               13 (text)
                      424 PRECALL                  1
                      428 CALL                     1
                      438 STORE_FAST              11 (result)
          
-          52         440 LOAD_CONST              11 ('error_msg')
+          50         440 LOAD_CONST              11 ('error_msg')
                      442 LOAD_FAST               11 (result)
                      444 CONTAINS_OP              0
                      446 POP_JUMP_FORWARD_IF_FALSE    11 (to 470)
          
-          53         448 LOAD_FAST               11 (result)
+          51         448 LOAD_FAST               11 (result)
                      450 LOAD_CONST              11 ('error_msg')
                      452 BINARY_SUBSCR
                      462 LOAD_CONST              12 ('Failed')
                      464 LOAD_CONST              13 (('error', 'Status'))
                      466 BUILD_CONST_KEY_MAP      2
                      468 RETURN_VALUE
          
-          56     >>  470 LOAD_CONST              14 ('mot')
+          54     >>  470 LOAD_CONST              14 ('mot')
                      472 LOAD_FAST               11 (result)
                      474 CONTAINS_OP              0
                      476 POP_JUMP_FORWARD_IF_FALSE   157 (to 792)
          
-          57         478 LOAD_GLOBAL             11 (NULL + open)
+          55         478 LOAD_GLOBAL             11 (NULL + open)
                      490 LOAD_FAST                2 (des_path)
                      492 LOAD_CONST              15 ('/')
                      494 BINARY_OP                0 (+)
                      498 LOAD_FAST                5 (file_name)
                      500 LOAD_CONST               0 (None)
                      502 LOAD_CONST              16 (-3)
                      504 BUILD_SLICE              2
@@ -462,66 +482,66 @@
                      520 LOAD_CONST              14 ('mot')
                      522 BINARY_OP                0 (+)
                      526 LOAD_CONST              17 ('w')
                      528 PRECALL                  2
                      532 CALL                     2
                      542 STORE_FAST              12 (motFile)
          
-          58         544 LOAD_FAST               12 (motFile)
+          56         544 LOAD_FAST               12 (motFile)
                      546 LOAD_METHOD             14 (writelines)
                      568 LOAD_FAST               11 (result)
                      570 LOAD_CONST              14 ('mot')
                      572 BINARY_SUBSCR
                      582 LOAD_CONST              18 ('h1')
                      584 BINARY_SUBSCR
                      594 PRECALL                  1
                      598 CALL                     1
                      608 POP_TOP
          
-          59         610 LOAD_FAST               12 (motFile)
+          57         610 LOAD_FAST               12 (motFile)
                      612 LOAD_METHOD             14 (writelines)
                      634 LOAD_FAST               11 (result)
                      636 LOAD_CONST              14 ('mot')
                      638 BINARY_SUBSCR
                      648 LOAD_CONST              19 ('h2')
                      650 BINARY_SUBSCR
                      660 PRECALL                  1
                      664 CALL                     1
                      674 POP_TOP
          
-          60         676 LOAD_FAST               11 (result)
+          58         676 LOAD_FAST               11 (result)
                      678 LOAD_CONST              14 ('mot')
                      680 BINARY_SUBSCR
                      690 LOAD_CONST              20 ('data')
                      692 BINARY_SUBSCR
                      702 GET_ITER
                  >>  704 FOR_ITER                23 (to 752)
                      706 STORE_FAST              13 (d)
          
-          61         708 LOAD_FAST               12 (motFile)
+          59         708 LOAD_FAST               12 (motFile)
                      710 LOAD_METHOD             14 (writelines)
                      732 LOAD_FAST               13 (d)
                      734 PRECALL                  1
                      738 CALL                     1
                      748 POP_TOP
                      750 JUMP_BACKWARD           24 (to 704)
          
-          62     >>  752 LOAD_FAST               12 (motFile)
+          60     >>  752 LOAD_FAST               12 (motFile)
                      754 LOAD_METHOD             15 (close)
                      776 PRECALL                  0
                      780 CALL                     0
                      790 POP_TOP
          
-          64     >>  792 LOAD_CONST              21 ('trc')
+          62     >>  792 LOAD_CONST              21 ('trc')
                      794 LOAD_FAST               11 (result)
                      796 CONTAINS_OP              0
                      798 EXTENDED_ARG             1
                      800 POP_JUMP_FORWARD_IF_FALSE   256 (to 1314)
          
-          65         802 LOAD_GLOBAL             11 (NULL + open)
+          63         802 LOAD_GLOBAL             11 (NULL + open)
                      814 LOAD_FAST                2 (des_path)
                      816 LOAD_CONST              15 ('/')
                      818 BINARY_OP                0 (+)
                      822 LOAD_FAST                5 (file_name)
                      824 LOAD_CONST               0 (None)
                      826 LOAD_CONST              16 (-3)
                      828 BUILD_SLICE              2
@@ -530,125 +550,143 @@
                      844 LOAD_CONST              21 ('trc')
                      846 BINARY_OP                0 (+)
                      850 LOAD_CONST              17 ('w')
                      852 PRECALL                  2
                      856 CALL                     2
                      866 STORE_FAST              14 (trcFile)
          
-          66         868 LOAD_FAST               14 (trcFile)
+          64         868 LOAD_FAST               14 (trcFile)
                      870 LOAD_METHOD             14 (writelines)
                      892 LOAD_FAST               11 (result)
                      894 LOAD_CONST              21 ('trc')
                      896 BINARY_SUBSCR
                      906 LOAD_CONST              18 ('h1')
                      908 BINARY_SUBSCR
                      918 PRECALL                  1
                      922 CALL                     1
                      932 POP_TOP
          
-          67         934 LOAD_FAST               14 (trcFile)
+          65         934 LOAD_FAST               14 (trcFile)
                      936 LOAD_METHOD             14 (writelines)
                      958 LOAD_FAST               11 (result)
                      960 LOAD_CONST              21 ('trc')
                      962 BINARY_SUBSCR
                      972 LOAD_CONST              19 ('h2')
                      974 BINARY_SUBSCR
                      984 PRECALL                  1
                      988 CALL                     1
                      998 POP_TOP
          
-          68        1000 LOAD_FAST               14 (trcFile)
+          66        1000 LOAD_FAST               14 (trcFile)
                     1002 LOAD_METHOD             14 (writelines)
                     1024 LOAD_FAST               11 (result)
                     1026 LOAD_CONST              21 ('trc')
                     1028 BINARY_SUBSCR
                     1038 LOAD_CONST              22 ('h3')
                     1040 BINARY_SUBSCR
                     1050 PRECALL                  1
                     1054 CALL                     1
                     1064 POP_TOP
          
-          69        1066 LOAD_FAST               14 (trcFile)
+          67        1066 LOAD_FAST               14 (trcFile)
                     1068 LOAD_METHOD             14 (writelines)
                     1090 LOAD_FAST               11 (result)
                     1092 LOAD_CONST              21 ('trc')
                     1094 BINARY_SUBSCR
                     1104 LOAD_CONST              23 ('h4')
                     1106 BINARY_SUBSCR
                     1116 PRECALL                  1
                     1120 CALL                     1
                     1130 POP_TOP
          
-          70        1132 LOAD_FAST               14 (trcFile)
+          68        1132 LOAD_FAST               14 (trcFile)
                     1134 LOAD_METHOD             14 (writelines)
                     1156 LOAD_FAST               11 (result)
                     1158 LOAD_CONST              21 ('trc')
                     1160 BINARY_SUBSCR
                     1170 LOAD_CONST              24 ('h5')
                     1172 BINARY_SUBSCR
                     1182 PRECALL                  1
                     1186 CALL                     1
                     1196 POP_TOP
          
-          71        1198 LOAD_FAST               11 (result)
+          69        1198 LOAD_FAST               11 (result)
                     1200 LOAD_CONST              21 ('trc')
                     1202 BINARY_SUBSCR
                     1212 LOAD_CONST              20 ('data')
                     1214 BINARY_SUBSCR
                     1224 GET_ITER
                  >> 1226 FOR_ITER                23 (to 1274)
                     1228 STORE_FAST              13 (d)
          
-          72        1230 LOAD_FAST               14 (trcFile)
+          70        1230 LOAD_FAST               14 (trcFile)
                     1232 LOAD_METHOD             14 (writelines)
                     1254 LOAD_FAST               13 (d)
                     1256 PRECALL                  1
                     1260 CALL                     1
                     1270 POP_TOP
                     1272 JUMP_BACKWARD           24 (to 1226)
          
-          73     >> 1274 LOAD_FAST               14 (trcFile)
+          71     >> 1274 LOAD_FAST               14 (trcFile)
                     1276 LOAD_METHOD             15 (close)
                     1298 PRECALL                  0
                     1302 CALL                     0
                     1312 POP_TOP
          
-          75     >> 1314 LOAD_GLOBAL             33 (NULL + GenerateOutput)
+          73     >> 1314 LOAD_GLOBAL             33 (NULL + GenerateOutput)
                     1326 LOAD_FAST               11 (result)
                     1328 LOAD_CONST              25 ('c3d')
                     1330 BINARY_SUBSCR
                     1340 PRECALL                  1
                     1344 CALL                     1
                     1354 RETURN_VALUE
                  >> 1356 PUSH_EXC_INFO
          
-          77        1358 POP_TOP
-         
-          78        1360 LOAD_CONST              26 ('Status')
-                    1362 LOAD_CONST              12 ('Failed')
-                    1364 BUILD_MAP                1
-                    1366 SWAP                     2
-                    1368 POP_EXCEPT
-                    1370 RETURN_VALUE
-                 >> 1372 COPY                     3
-                    1374 POP_EXCEPT
-                    1376 RERAISE                  1
+          75        1358 LOAD_GLOBAL             34 (Exception)
+                    1370 CHECK_EXC_MATCH
+                    1372 POP_JUMP_FORWARD_IF_FALSE    15 (to 1404)
+                    1374 STORE_FAST              15 (e)
+         
+          76        1376 LOAD_CONST              12 ('Failed')
+         
+          77        1378 LOAD_FAST               15 (e)
+         
+          76        1380 LOAD_CONST              26 (('Status', 'error'))
+                    1382 BUILD_CONST_KEY_MAP      2
+                    1384 SWAP                     2
+                    1386 POP_EXCEPT
+                    1388 LOAD_CONST               0 (None)
+                    1390 STORE_FAST              15 (e)
+                    1392 DELETE_FAST             15 (e)
+                    1394 RETURN_VALUE
+                 >> 1396 LOAD_CONST               0 (None)
+                    1398 STORE_FAST              15 (e)
+                    1400 DELETE_FAST             15 (e)
+                    1402 RERAISE                  1
+         
+          75     >> 1404 RERAISE                  0
+                 >> 1406 COPY                     3
+                    1408 POP_EXCEPT
+                    1410 RERAISE                  1
          ExceptionTable:
            158 to 196 -> 366 [1] lasti
            198 to 294 -> 320 [2] lasti
            296 to 318 -> 366 [1] lasti
            320 to 326 -> 328 [4] lasti
            328 to 332 -> 366 [1] lasti
            334 to 334 -> 328 [4] lasti
            336 to 340 -> 366 [1] lasti
            366 to 372 -> 374 [3] lasti
            380 to 380 -> 374 [3] lasti
            390 to 466 -> 1356 [0]
            470 to 1352 -> 1356 [0]
-           1356 to 1366 -> 1372 [1] lasti
+           1356 to 1374 -> 1406 [1] lasti
+           1376 to 1382 -> 1396 [1] lasti
+           1384 to 1384 -> 1406 [1] lasti
+           1396 to 1404 -> 1406 [1] lasti
          consts
             None
             'https://c3dtools.com/API/getOpenSimData'
             'api_key'
             'rb'
             'B'
             True
@@ -668,396 +706,411 @@
             'h2'
             'data'
             'trc'
             'h3'
             'h4'
             'h5'
             'c3d'
-            'Status'
-         names      ('os', 'path', 'basename', 'stat', 'st_size', 'open', 'tqdm', 'CallbackIOWrapper', 'update', 'requests', 'post', 'json', 'loads', 'text', 'writelines', 'close', 'GenerateOutput')
-         varnames   ('Token', 'file_path', 'des_path', 'API_URL', 'data', 'file_name', 'file_size', 'f', 't', 'wrapped_file', 'resp', 'result', 'motFile', 'd', 'trcFile')
+            ('Status', 'error')
+         names      ('os', 'path', 'basename', 'stat', 'st_size', 'open', 'tqdm', 'CallbackIOWrapper', 'update', 'requests', 'post', 'json', 'loads', 'text', 'writelines', 'close', 'GenerateOutput', 'Exception')
+         varnames   ('Token', 'file_path', 'des_path', 'API_URL', 'data', 'file_name', 'file_size', 'f', 't', 'wrapped_file', 'resp', 'result', 'motFile', 'd', 'trcFile', 'e')
          freevars   ()
          cellvars   ()
          filename   '\\Python311\\Lib\\site-packages\\pyc3dtools\\pyc3dtools.py'
          name       'getTRCMot'
-         firstlineno 39
+         firstlineno 37
          lnotab
             0x0201040108013e013201220128012c0134fe2eff2e0502013202080116
             03080142014201420120012c0128020a0142014201420142014201420120
-            012c0128022c020201
+            012c0128022c021201020102ff18ff
       code
          argcount  : 1
-         nlocals   : 18
+         nlocals   : 23
          stacksize : 12
          flags     : 3
          code
-            0x87128713871497007c006401190000000000000000008a127c00640219
+            0x87178718871997007c006401190000000000000000008a177c00640219
             0000000000000000007d017c006403190000000000000000007d027c0064
             04190000000000000000007d037c006405190000000000000000007d047c
             006406190000000000000000007d057401000000000000000000006a0100
             000000000000007c01a6010000ab0100000000000000007d067c06640064
             0085027c026400640085026603190000000000000000007d067c067c0064
-            073c00000088126601640884087405000000000000000000007407000000
-            000000000000008912a6010000ab010000000000000000a6010000ab0100
+            073c00000088176601640884087405000000000000000000007407000000
+            000000000000008917a6010000ab010000000000000000a6010000ab0100
             000000000000004400a6000000ab00000000000000000064091900000000
-            00000000008a14881288146602640a840874050000000000000000000074
-            07000000000000000000008912891419000000000000000000640b190000
+            00000000008a19881788196602640a840874050000000000000000000074
+            07000000000000000000008917891919000000000000000000640b190000
             00000000000000a6010000ab010000000000000000a6010000ab01000000
             00000000004400a6000000ab000000000000000000640919000000000000
-            0000007d07881288146602640c8408740500000000000000000000740700
-            0000000000000000008912891419000000000000000000640b1900000000
+            0000007d07881788196602640c8408740500000000000000000000740700
+            0000000000000000008917891919000000000000000000640b1900000000
             0000000000a6010000ab010000000000000000a6010000ab010000000000
             0000004400a6000000ab0000000000000000006409190000000000000000
-            007d08881288146602640d84087405000000000000000000007407000000
-            000000000000008912891419000000000000000000640b19000000000000
+            007d08881788196602640d84087405000000000000000000007407000000
+            000000000000008917891919000000000000000000640b19000000000000
             000000a6010000ab010000000000000000a6010000ab0100000000000000
             004400a6000000ab0000000000000000006409190000000000000000007d
-            09881288146602640e840874050000000000000000000074070000000000
-            00000000008912891419000000000000000000640b190000000000000000
+            09881788196602640e840874050000000000000000000074070000000000
+            00000000008917891919000000000000000000640b190000000000000000
             00a6010000ab010000000000000000a6010000ab01000000000000000044
             00a6000000ab0000000000000000006409190000000000000000007d0a89
-            12891419000000000000000000640b190000000000000000007c07190000
-            00000000000000640f190000000000000000007d0b891289141900000000
+            17891919000000000000000000640b190000000000000000007c07190000
+            00000000000000640f190000000000000000007d0b891789191900000000
             0000000000640b190000000000000000007c081900000000000000000064
-            0f190000000000000000006409190000000000000000007d0c8912891419
+            0f190000000000000000006409190000000000000000007d0c8917891919
             000000000000000000640b190000000000000000007c0919000000000000
             000000640f190000000000000000006409190000000000000000007d0d89
-            12891419000000000000000000640b190000000000000000007c0a190000
+            17891919000000000000000000640b190000000000000000007c0a190000
             00000000000000640f190000000000000000006409190000000000000000
-            007d0e881266016410840874050000000000000000000074070000000000
-            00000000008912a6010000ab010000000000000000a6010000ab01000000
+            007d0e881766016410840874050000000000000000000074070000000000
+            00000000008917a6010000ab010000000000000000a6010000ab01000000
             00000000004400a6000000ab000000000000000000640919000000000000
-            0000008a1388128813660264118408740500000000000000000000740700
-            0000000000000000008912891319000000000000000000640b1900000000
+            0000008a1888178818660264118408740500000000000000000000740700
+            0000000000000000008917891819000000000000000000640b1900000000
             0000000000a6010000ab010000000000000000a6010000ab010000000000
             0000004400a6000000ab0000000000000000006409190000000000000000
-            007d0f8912891319000000000000000000640b190000000000000000007c
+            007d0f8917891819000000000000000000640b190000000000000000007c
             0f19000000000000000000640f190000000000000000007d107c0544005d
             757d117c116412190000000000000000007c1164133c0000007401000000
             000000000000006a0100000000000000007c116414190000000000000000
             006400640085021900000000000000000064006400850219000000000000
             000000740800000000000000000000ac15a6020000ab0200000000000000
             007c1164143c0000007401000000000000000000006a0100000000000000
             007c11641619000000000000000000640064008502190000000000000000
             0064006400850219000000000000000000740800000000000000000000ac
-            15a6020000ab0200000000000000007c1164163c0000008c76641789127c
-            067c017c037c047c057c0b7c107c0c7c0e7c0d670264189c0b5300
-                       0 MAKE_CELL               18 (GP)
-                       2 MAKE_CELL               19 (gp_analog_lbl_i)
-                       4 MAKE_CELL               20 (gp_point_lbl_i)
+            15a6020000ab0200000000000000007c1164163c0000008c767401000000
+            000000000000006a0100000000000000007c03a6010000ab010000000000
+            0000007d0367007d127c0344005dc07d1167007d13740500000000000000
+            000000740b000000000000000000007407000000000000000000007c11a6
+            010000ab0100000000000000007407000000000000000000007c10a60100
+            00ab0100000000000000007a0b0000a6010000ab01000000000000000064
+            177a0a0000a6010000ab01000000000000000044005d6a7d1467007d1574
+            05000000000000000000007c147407000000000000000000007c10a60100
+            00ab0100000000000000007a0500007c1464177a00000074070000000000
+            00000000007c10a6010000ab0100000000000000007a050000a6020000ab
+            02000000000000000044005d1d7d167c15a0060000000000000000000000
+            0000000000000000007c117c1619000000000000000000a6010000ab0100
+            0000000000000001008c1e7c13a006000000000000000000000000000000
+            00000000007c15a6010000ab01000000000000000001008c6b7c12a00600
+            000000000000000000000000000000000000007c13a6010000ab01000000
+            000000000001008cc17c127d03641889177c067c017c037c047c057c0b7c
+            107c0c7c0e7c0d670264199c0b5300
+                       0 MAKE_CELL               23 (GP)
+                       2 MAKE_CELL               24 (gp_analog_lbl_i)
+                       4 MAKE_CELL               25 (gp_point_lbl_i)
          
-          84           6 RESUME                   0
+          83           6 RESUME                   0
          
-          85           8 LOAD_FAST                0 (result)
+          84           8 LOAD_FAST                0 (result)
                       10 LOAD_CONST               1 ('GP')
                       12 BINARY_SUBSCR
-                      22 STORE_DEREF             18 (GP)
+                      22 STORE_DEREF             23 (GP)
          
-          86          24 LOAD_FAST                0 (result)
+          85          24 LOAD_FAST                0 (result)
                       26 LOAD_CONST               2 ('Point')
                       28 BINARY_SUBSCR
                       38 STORE_FAST               1 (Point)
          
-          87          40 LOAD_FAST                0 (result)
+          86          40 LOAD_FAST                0 (result)
                       42 LOAD_CONST               3 ('Real_marker_index')
                       44 BINARY_SUBSCR
                       54 STORE_FAST               2 (Real_marker_index)
          
-          88          56 LOAD_FAST                0 (result)
+          87          56 LOAD_FAST                0 (result)
                       58 LOAD_CONST               4 ('Analog')
                       60 BINARY_SUBSCR
                       70 STORE_FAST               3 (Analog)
          
-          89          72 LOAD_FAST                0 (result)
+          88          72 LOAD_FAST                0 (result)
                       74 LOAD_CONST               5 ('Header')
                       76 BINARY_SUBSCR
                       86 STORE_FAST               4 (Header)
          
-          90          88 LOAD_FAST                0 (result)
+          89          88 LOAD_FAST                0 (result)
                       90 LOAD_CONST               6 ('Forceplate_list')
                       92 BINARY_SUBSCR
                      102 STORE_FAST               5 (Forceplates)
          
-          91         104 LOAD_GLOBAL              1 (NULL + np)
+          90         104 LOAD_GLOBAL              1 (NULL + np)
                      116 LOAD_ATTR                1 (array)
                      126 LOAD_FAST                1 (Point)
                      128 PRECALL                  1
                      132 CALL                     1
                      142 STORE_FAST               6 (Real_Markers)
          
-          92         144 LOAD_FAST                6 (Real_Markers)
+          91         144 LOAD_FAST                6 (Real_Markers)
                      146 LOAD_CONST               0 (None)
                      148 LOAD_CONST               0 (None)
                      150 BUILD_SLICE              2
                      152 LOAD_FAST                2 (Real_marker_index)
                      154 LOAD_CONST               0 (None)
                      156 LOAD_CONST               0 (None)
                      158 BUILD_SLICE              2
                      160 BUILD_TUPLE              3
                      162 BINARY_SUBSCR
                      172 STORE_FAST               6 (Real_Markers)
          
-          93         174 LOAD_FAST                6 (Real_Markers)
+          92         174 LOAD_FAST                6 (Real_Markers)
                      176 LOAD_FAST                0 (result)
                      178 LOAD_CONST               7 ('Markers')
                      180 STORE_SUBSCR
          
-          96         184 LOAD_CLOSURE            18 (GP)
+          95         184 LOAD_CLOSURE            23 (GP)
                      186 BUILD_TUPLE              1
-                     188 LOAD_CONST               8 (<code object <listcomp>, file "\Python311\Lib\site-packages\pyc3dtools\pyc3dtools.py", line 96>)
+                     188 LOAD_CONST               8 (<code object <listcomp>, file "\Python311\Lib\site-packages\pyc3dtools\pyc3dtools.py", line 95>)
                      190 MAKE_FUNCTION            8 (closure)
          
-          97         192 LOAD_GLOBAL              5 (NULL + range)
+          96         192 LOAD_GLOBAL              5 (NULL + range)
                      204 LOAD_GLOBAL              7 (NULL + len)
-                     216 LOAD_DEREF              18 (GP)
+                     216 LOAD_DEREF              23 (GP)
                      218 PRECALL                  1
                      222 CALL                     1
                      232 PRECALL                  1
                      236 CALL                     1
          
-          96         246 GET_ITER
+          95         246 GET_ITER
                      248 PRECALL                  0
                      252 CALL                     0
          
-          99         262 LOAD_CONST               9 (0)
+          98         262 LOAD_CONST               9 (0)
          
-          96         264 BINARY_SUBSCR
-                     274 STORE_DEREF             20 (gp_point_lbl_i)
+          95         264 BINARY_SUBSCR
+                     274 STORE_DEREF             25 (gp_point_lbl_i)
          
-         100         276 LOAD_CLOSURE            18 (GP)
-                     278 LOAD_CLOSURE            20 (gp_point_lbl_i)
+          99         276 LOAD_CLOSURE            23 (GP)
+                     278 LOAD_CLOSURE            25 (gp_point_lbl_i)
                      280 BUILD_TUPLE              2
-                     282 LOAD_CONST              10 (<code object <listcomp>, file "\Python311\Lib\site-packages\pyc3dtools\pyc3dtools.py", line 100>)
+                     282 LOAD_CONST              10 (<code object <listcomp>, file "\Python311\Lib\site-packages\pyc3dtools\pyc3dtools.py", line 99>)
                      284 MAKE_FUNCTION            8 (closure)
          
-         101         286 LOAD_GLOBAL              5 (NULL + range)
+         100         286 LOAD_GLOBAL              5 (NULL + range)
                      298 LOAD_GLOBAL              7 (NULL + len)
-                     310 LOAD_DEREF              18 (GP)
-                     312 LOAD_DEREF              20 (gp_point_lbl_i)
+                     310 LOAD_DEREF              23 (GP)
+                     312 LOAD_DEREF              25 (gp_point_lbl_i)
                      314 BINARY_SUBSCR
                      324 LOAD_CONST              11 ('List_Parameters')
                      326 BINARY_SUBSCR
                      336 PRECALL                  1
                      340 CALL                     1
                      350 PRECALL                  1
                      354 CALL                     1
          
-         100         364 GET_ITER
+          99         364 GET_ITER
                      366 PRECALL                  0
                      370 CALL                     0
          
-         103         380 LOAD_CONST               9 (0)
+         102         380 LOAD_CONST               9 (0)
          
-         100         382 BINARY_SUBSCR
+          99         382 BINARY_SUBSCR
                      392 STORE_FAST               7 (gp_point_lbl_ii)
          
-         104         394 LOAD_CLOSURE            18 (GP)
-                     396 LOAD_CLOSURE            20 (gp_point_lbl_i)
+         103         394 LOAD_CLOSURE            23 (GP)
+                     396 LOAD_CLOSURE            25 (gp_point_lbl_i)
                      398 BUILD_TUPLE              2
-                     400 LOAD_CONST              12 (<code object <listcomp>, file "\Python311\Lib\site-packages\pyc3dtools\pyc3dtools.py", line 104>)
+                     400 LOAD_CONST              12 (<code object <listcomp>, file "\Python311\Lib\site-packages\pyc3dtools\pyc3dtools.py", line 103>)
                      402 MAKE_FUNCTION            8 (closure)
          
-         105         404 LOAD_GLOBAL              5 (NULL + range)
+         104         404 LOAD_GLOBAL              5 (NULL + range)
                      416 LOAD_GLOBAL              7 (NULL + len)
-                     428 LOAD_DEREF              18 (GP)
-                     430 LOAD_DEREF              20 (gp_point_lbl_i)
+                     428 LOAD_DEREF              23 (GP)
+                     430 LOAD_DEREF              25 (gp_point_lbl_i)
                      432 BINARY_SUBSCR
                      442 LOAD_CONST              11 ('List_Parameters')
                      444 BINARY_SUBSCR
                      454 PRECALL                  1
                      458 CALL                     1
                      468 PRECALL                  1
                      472 CALL                     1
          
-         104         482 GET_ITER
+         103         482 GET_ITER
                      484 PRECALL                  0
                      488 CALL                     0
          
-         107         498 LOAD_CONST               9 (0)
+         106         498 LOAD_CONST               9 (0)
          
-         104         500 BINARY_SUBSCR
+         103         500 BINARY_SUBSCR
                      510 STORE_FAST               8 (gp_point_unit_i)
          
-         108         512 LOAD_CLOSURE            18 (GP)
-                     514 LOAD_CLOSURE            20 (gp_point_lbl_i)
+         107         512 LOAD_CLOSURE            23 (GP)
+                     514 LOAD_CLOSURE            25 (gp_point_lbl_i)
                      516 BUILD_TUPLE              2
-                     518 LOAD_CONST              13 (<code object <listcomp>, file "\Python311\Lib\site-packages\pyc3dtools\pyc3dtools.py", line 108>)
+                     518 LOAD_CONST              13 (<code object <listcomp>, file "\Python311\Lib\site-packages\pyc3dtools\pyc3dtools.py", line 107>)
                      520 MAKE_FUNCTION            8 (closure)
          
-         109         522 LOAD_GLOBAL              5 (NULL + range)
+         108         522 LOAD_GLOBAL              5 (NULL + range)
                      534 LOAD_GLOBAL              7 (NULL + len)
-                     546 LOAD_DEREF              18 (GP)
-                     548 LOAD_DEREF              20 (gp_point_lbl_i)
+                     546 LOAD_DEREF              23 (GP)
+                     548 LOAD_DEREF              25 (gp_point_lbl_i)
                      550 BINARY_SUBSCR
                      560 LOAD_CONST              11 ('List_Parameters')
                      562 BINARY_SUBSCR
                      572 PRECALL                  1
                      576 CALL                     1
                      586 PRECALL                  1
                      590 CALL                     1
          
-         108         600 GET_ITER
+         107         600 GET_ITER
                      602 PRECALL                  0
                      606 CALL                     0
          
-         111         616 LOAD_CONST               9 (0)
+         110         616 LOAD_CONST               9 (0)
          
-         108         618 BINARY_SUBSCR
+         107         618 BINARY_SUBSCR
                      628 STORE_FAST               9 (gp_point_Yscreen_i)
          
-         112         630 LOAD_CLOSURE            18 (GP)
-                     632 LOAD_CLOSURE            20 (gp_point_lbl_i)
+         111         630 LOAD_CLOSURE            23 (GP)
+                     632 LOAD_CLOSURE            25 (gp_point_lbl_i)
                      634 BUILD_TUPLE              2
-                     636 LOAD_CONST              14 (<code object <listcomp>, file "\Python311\Lib\site-packages\pyc3dtools\pyc3dtools.py", line 112>)
+                     636 LOAD_CONST              14 (<code object <listcomp>, file "\Python311\Lib\site-packages\pyc3dtools\pyc3dtools.py", line 111>)
                      638 MAKE_FUNCTION            8 (closure)
          
-         113         640 LOAD_GLOBAL              5 (NULL + range)
+         112         640 LOAD_GLOBAL              5 (NULL + range)
                      652 LOAD_GLOBAL              7 (NULL + len)
-                     664 LOAD_DEREF              18 (GP)
-                     666 LOAD_DEREF              20 (gp_point_lbl_i)
+                     664 LOAD_DEREF              23 (GP)
+                     666 LOAD_DEREF              25 (gp_point_lbl_i)
                      668 BINARY_SUBSCR
                      678 LOAD_CONST              11 ('List_Parameters')
                      680 BINARY_SUBSCR
                      690 PRECALL                  1
                      694 CALL                     1
                      704 PRECALL                  1
                      708 CALL                     1
          
-         112         718 GET_ITER
+         111         718 GET_ITER
                      720 PRECALL                  0
                      724 CALL                     0
          
-         115         734 LOAD_CONST               9 (0)
+         114         734 LOAD_CONST               9 (0)
          
-         112         736 BINARY_SUBSCR
+         111         736 BINARY_SUBSCR
                      746 STORE_FAST              10 (gp_point_Xscreen_i)
          
-         116         748 LOAD_DEREF              18 (GP)
-                     750 LOAD_DEREF              20 (gp_point_lbl_i)
+         115         748 LOAD_DEREF              23 (GP)
+                     750 LOAD_DEREF              25 (gp_point_lbl_i)
                      752 BINARY_SUBSCR
                      762 LOAD_CONST              11 ('List_Parameters')
                      764 BINARY_SUBSCR
                      774 LOAD_FAST                7 (gp_point_lbl_ii)
                      776 BINARY_SUBSCR
                      786 LOAD_CONST              15 ('Param_data')
                      788 BINARY_SUBSCR
                      798 STORE_FAST              11 (Markers_lbl)
          
-         117         800 LOAD_DEREF              18 (GP)
-                     802 LOAD_DEREF              20 (gp_point_lbl_i)
+         116         800 LOAD_DEREF              23 (GP)
+                     802 LOAD_DEREF              25 (gp_point_lbl_i)
                      804 BINARY_SUBSCR
                      814 LOAD_CONST              11 ('List_Parameters')
                      816 BINARY_SUBSCR
                      826 LOAD_FAST                8 (gp_point_unit_i)
                      828 BINARY_SUBSCR
                      838 LOAD_CONST              15 ('Param_data')
                      840 BINARY_SUBSCR
                      850 LOAD_CONST               9 (0)
                      852 BINARY_SUBSCR
                      862 STORE_FAST              12 (Markers_Units)
          
-         118         864 LOAD_DEREF              18 (GP)
-                     866 LOAD_DEREF              20 (gp_point_lbl_i)
+         117         864 LOAD_DEREF              23 (GP)
+                     866 LOAD_DEREF              25 (gp_point_lbl_i)
                      868 BINARY_SUBSCR
                      878 LOAD_CONST              11 ('List_Parameters')
                      880 BINARY_SUBSCR
                      890 LOAD_FAST                9 (gp_point_Yscreen_i)
                      892 BINARY_SUBSCR
                      902 LOAD_CONST              15 ('Param_data')
                      904 BINARY_SUBSCR
                      914 LOAD_CONST               9 (0)
                      916 BINARY_SUBSCR
                      926 STORE_FAST              13 (Markers_YSCREEN)
          
-         119         928 LOAD_DEREF              18 (GP)
-                     930 LOAD_DEREF              20 (gp_point_lbl_i)
+         118         928 LOAD_DEREF              23 (GP)
+                     930 LOAD_DEREF              25 (gp_point_lbl_i)
                      932 BINARY_SUBSCR
                      942 LOAD_CONST              11 ('List_Parameters')
                      944 BINARY_SUBSCR
                      954 LOAD_FAST               10 (gp_point_Xscreen_i)
                      956 BINARY_SUBSCR
                      966 LOAD_CONST              15 ('Param_data')
                      968 BINARY_SUBSCR
                      978 LOAD_CONST               9 (0)
                      980 BINARY_SUBSCR
                      990 STORE_FAST              14 (Markers_XSCREEN)
          
-         122         992 LOAD_CLOSURE            18 (GP)
+         121         992 LOAD_CLOSURE            23 (GP)
                      994 BUILD_TUPLE              1
-                     996 LOAD_CONST              16 (<code object <listcomp>, file "\Python311\Lib\site-packages\pyc3dtools\pyc3dtools.py", line 122>)
+                     996 LOAD_CONST              16 (<code object <listcomp>, file "\Python311\Lib\site-packages\pyc3dtools\pyc3dtools.py", line 121>)
                      998 MAKE_FUNCTION            8 (closure)
          
-         123        1000 LOAD_GLOBAL              5 (NULL + range)
+         122        1000 LOAD_GLOBAL              5 (NULL + range)
                     1012 LOAD_GLOBAL              7 (NULL + len)
-                    1024 LOAD_DEREF              18 (GP)
+                    1024 LOAD_DEREF              23 (GP)
                     1026 PRECALL                  1
                     1030 CALL                     1
                     1040 PRECALL                  1
                     1044 CALL                     1
          
-         122        1054 GET_ITER
+         121        1054 GET_ITER
                     1056 PRECALL                  0
                     1060 CALL                     0
          
-         125        1070 LOAD_CONST               9 (0)
+         124        1070 LOAD_CONST               9 (0)
          
-         122        1072 BINARY_SUBSCR
-                    1082 STORE_DEREF             19 (gp_analog_lbl_i)
+         121        1072 BINARY_SUBSCR
+                    1082 STORE_DEREF             24 (gp_analog_lbl_i)
          
-         126        1084 LOAD_CLOSURE            18 (GP)
-                    1086 LOAD_CLOSURE            19 (gp_analog_lbl_i)
+         125        1084 LOAD_CLOSURE            23 (GP)
+                    1086 LOAD_CLOSURE            24 (gp_analog_lbl_i)
                     1088 BUILD_TUPLE              2
-                    1090 LOAD_CONST              17 (<code object <listcomp>, file "\Python311\Lib\site-packages\pyc3dtools\pyc3dtools.py", line 126>)
+                    1090 LOAD_CONST              17 (<code object <listcomp>, file "\Python311\Lib\site-packages\pyc3dtools\pyc3dtools.py", line 125>)
                     1092 MAKE_FUNCTION            8 (closure)
          
-         127        1094 LOAD_GLOBAL              5 (NULL + range)
+         126        1094 LOAD_GLOBAL              5 (NULL + range)
                     1106 LOAD_GLOBAL              7 (NULL + len)
-                    1118 LOAD_DEREF              18 (GP)
-                    1120 LOAD_DEREF              19 (gp_analog_lbl_i)
+                    1118 LOAD_DEREF              23 (GP)
+                    1120 LOAD_DEREF              24 (gp_analog_lbl_i)
                     1122 BINARY_SUBSCR
                     1132 LOAD_CONST              11 ('List_Parameters')
                     1134 BINARY_SUBSCR
                     1144 PRECALL                  1
                     1148 CALL                     1
                     1158 PRECALL                  1
                     1162 CALL                     1
          
-         126        1172 GET_ITER
+         125        1172 GET_ITER
                     1174 PRECALL                  0
                     1178 CALL                     0
          
-         129        1188 LOAD_CONST               9 (0)
+         128        1188 LOAD_CONST               9 (0)
          
-         126        1190 BINARY_SUBSCR
+         125        1190 BINARY_SUBSCR
                     1200 STORE_FAST              15 (gp_analog_lbl_ii)
          
-         130        1202 LOAD_DEREF              18 (GP)
-                    1204 LOAD_DEREF              19 (gp_analog_lbl_i)
+         129        1202 LOAD_DEREF              23 (GP)
+                    1204 LOAD_DEREF              24 (gp_analog_lbl_i)
                     1206 BINARY_SUBSCR
                     1216 LOAD_CONST              11 ('List_Parameters')
                     1218 BINARY_SUBSCR
                     1228 LOAD_FAST               15 (gp_analog_lbl_ii)
                     1230 BINARY_SUBSCR
                     1240 LOAD_CONST              15 ('Param_data')
                     1242 BINARY_SUBSCR
                     1252 STORE_FAST              16 (Analog_lbl)
          
-         134        1254 LOAD_FAST                5 (Forceplates)
+         133        1254 LOAD_FAST                5 (Forceplates)
                     1256 GET_ITER
                  >> 1258 FOR_ITER               117 (to 1494)
                     1260 STORE_FAST              17 (f)
          
-         135        1262 LOAD_FAST               17 (f)
+         134        1262 LOAD_FAST               17 (f)
                     1264 LOAD_CONST              18 ('orgin')
                     1266 BINARY_SUBSCR
                     1276 LOAD_FAST               17 (f)
                     1278 LOAD_CONST              19 ('Origin')
                     1280 STORE_SUBSCR
          
-         136        1284 LOAD_GLOBAL              1 (NULL + np)
+         135        1284 LOAD_GLOBAL              1 (NULL + np)
                     1296 LOAD_ATTR                1 (array)
                     1306 LOAD_FAST               17 (f)
                     1308 LOAD_CONST              20 ('COP')
                     1310 BINARY_SUBSCR
                     1320 LOAD_CONST               0 (None)
                     1322 LOAD_CONST               0 (None)
                     1324 BUILD_SLICE              2
@@ -1070,15 +1123,15 @@
                     1364 KW_NAMES                21
                     1366 PRECALL                  2
                     1370 CALL                     2
                     1380 LOAD_FAST               17 (f)
                     1382 LOAD_CONST              20 ('COP')
                     1384 STORE_SUBSCR
          
-         137        1388 LOAD_GLOBAL              1 (NULL + np)
+         136        1388 LOAD_GLOBAL              1 (NULL + np)
                     1400 LOAD_ATTR                1 (array)
                     1410 LOAD_FAST               17 (f)
                     1412 LOAD_CONST              22 ('GRF_VECTOR')
                     1414 BINARY_SUBSCR
                     1424 LOAD_CONST               0 (None)
                     1426 LOAD_CONST               0 (None)
                     1428 BUILD_SLICE              2
@@ -1092,41 +1145,133 @@
                     1470 PRECALL                  2
                     1474 CALL                     2
                     1484 LOAD_FAST               17 (f)
                     1486 LOAD_CONST              22 ('GRF_VECTOR')
                     1488 STORE_SUBSCR
                     1492 JUMP_BACKWARD          118 (to 1258)
          
-         142     >> 1494 LOAD_CONST              23 ('Success')
-         
-         143        1496 LOAD_DEREF              18 (GP)
-         
-         144        1498 LOAD_FAST                6 (Real_Markers)
-         
-         145        1500 LOAD_FAST                1 (Point)
-         
-         146        1502 LOAD_FAST                3 (Analog)
-         
-         147        1504 LOAD_FAST                4 (Header)
-         
-         148        1506 LOAD_FAST                5 (Forceplates)
-         
-         149        1508 LOAD_FAST               11 (Markers_lbl)
-         
-         150        1510 LOAD_FAST               16 (Analog_lbl)
-         
-         151        1512 LOAD_FAST               12 (Markers_Units)
-         
-         152        1514 LOAD_FAST               14 (Markers_XSCREEN)
-                    1516 LOAD_FAST               13 (Markers_YSCREEN)
-                    1518 BUILD_LIST               2
-         
-         141        1520 LOAD_CONST              24 (('Status', 'GP', 'Markers', 'Points', 'Analog', 'Header', 'ForcePlate', 'Markers Label', 'Analog Label', 'Units', 'Coordinate system'))
-                    1522 BUILD_CONST_KEY_MAP     11
-                    1524 RETURN_VALUE
+         140     >> 1494 LOAD_GLOBAL              1 (NULL + np)
+                    1506 LOAD_ATTR                1 (array)
+                    1516 LOAD_FAST                3 (Analog)
+                    1518 PRECALL                  1
+                    1522 CALL                     1
+                    1532 STORE_FAST               3 (Analog)
+         
+         141        1534 BUILD_LIST               0
+                    1536 STORE_FAST              18 (NewAnalog)
+         
+         142        1538 LOAD_FAST                3 (Analog)
+                    1540 GET_ITER
+                 >> 1542 FOR_ITER               192 (to 1928)
+                    1544 STORE_FAST              17 (f)
+         
+         143        1546 BUILD_LIST               0
+                    1548 STORE_FAST              19 (main_row)
+         
+         144        1550 LOAD_GLOBAL              5 (NULL + range)
+                    1562 LOAD_GLOBAL             11 (NULL + int)
+                    1574 LOAD_GLOBAL              7 (NULL + len)
+                    1586 LOAD_FAST               17 (f)
+                    1588 PRECALL                  1
+                    1592 CALL                     1
+                    1602 LOAD_GLOBAL              7 (NULL + len)
+                    1614 LOAD_FAST               16 (Analog_lbl)
+                    1616 PRECALL                  1
+                    1620 CALL                     1
+                    1630 BINARY_OP               11 (/)
+                    1634 PRECALL                  1
+                    1638 CALL                     1
+                    1648 LOAD_CONST              23 (1)
+                    1650 BINARY_OP               10 (-)
+                    1654 PRECALL                  1
+                    1658 CALL                     1
+                    1668 GET_ITER
+                 >> 1670 FOR_ITER               106 (to 1884)
+                    1672 STORE_FAST              20 (j)
+         
+         145        1674 BUILD_LIST               0
+                    1676 STORE_FAST              21 (row)
+         
+         146        1678 LOAD_GLOBAL              5 (NULL + range)
+                    1690 LOAD_FAST               20 (j)
+                    1692 LOAD_GLOBAL              7 (NULL + len)
+                    1704 LOAD_FAST               16 (Analog_lbl)
+                    1706 PRECALL                  1
+                    1710 CALL                     1
+                    1720 BINARY_OP                5 (*)
+                    1724 LOAD_FAST               20 (j)
+                    1726 LOAD_CONST              23 (1)
+                    1728 BINARY_OP                0 (+)
+                    1732 LOAD_GLOBAL              7 (NULL + len)
+                    1744 LOAD_FAST               16 (Analog_lbl)
+                    1746 PRECALL                  1
+                    1750 CALL                     1
+                    1760 BINARY_OP                5 (*)
+                    1764 PRECALL                  2
+                    1768 CALL                     2
+                    1778 GET_ITER
+                 >> 1780 FOR_ITER                29 (to 1840)
+                    1782 STORE_FAST              22 (k)
+         
+         147        1784 LOAD_FAST               21 (row)
+                    1786 LOAD_METHOD              6 (append)
+                    1808 LOAD_FAST               17 (f)
+                    1810 LOAD_FAST               22 (k)
+                    1812 BINARY_SUBSCR
+                    1822 PRECALL                  1
+                    1826 CALL                     1
+                    1836 POP_TOP
+                    1838 JUMP_BACKWARD           30 (to 1780)
+         
+         148     >> 1840 LOAD_FAST               19 (main_row)
+                    1842 LOAD_METHOD              6 (append)
+                    1864 LOAD_FAST               21 (row)
+                    1866 PRECALL                  1
+                    1870 CALL                     1
+                    1880 POP_TOP
+                    1882 JUMP_BACKWARD          107 (to 1670)
+         
+         150     >> 1884 LOAD_FAST               18 (NewAnalog)
+                    1886 LOAD_METHOD              6 (append)
+                    1908 LOAD_FAST               19 (main_row)
+                    1910 PRECALL                  1
+                    1914 CALL                     1
+                    1924 POP_TOP
+                    1926 JUMP_BACKWARD          193 (to 1542)
+         
+         152     >> 1928 LOAD_FAST               18 (NewAnalog)
+                    1930 STORE_FAST               3 (Analog)
+         
+         156        1932 LOAD_CONST              24 ('Success')
+         
+         157        1934 LOAD_DEREF              23 (GP)
+         
+         158        1936 LOAD_FAST                6 (Real_Markers)
+         
+         159        1938 LOAD_FAST                1 (Point)
+         
+         160        1940 LOAD_FAST                3 (Analog)
+         
+         161        1942 LOAD_FAST                4 (Header)
+         
+         162        1944 LOAD_FAST                5 (Forceplates)
+         
+         163        1946 LOAD_FAST               11 (Markers_lbl)
+         
+         164        1948 LOAD_FAST               16 (Analog_lbl)
+         
+         165        1950 LOAD_FAST               12 (Markers_Units)
+         
+         166        1952 LOAD_FAST               14 (Markers_XSCREEN)
+                    1954 LOAD_FAST               13 (Markers_YSCREEN)
+                    1956 BUILD_LIST               2
+         
+         155        1958 LOAD_CONST              25 (('Status', 'GP', 'Markers', 'Points', 'Analog', 'Header', 'ForcePlate', 'Markers Label', 'Analog Label', 'Units', 'Coordinate system'))
+                    1960 BUILD_CONST_KEY_MAP     11
+                    1962 RETURN_VALUE
          consts
             None
             'GP'
             'Point'
             'Real_marker_index'
             'Analog'
             'Header'
@@ -1138,359 +1283,361 @@
                stacksize : 4
                flags     : 19
                code
                   0x9501970067007c005d167d0189027c0119000000000000000000640019
                   00000000000000000064016b0200000000af147c0191028c175300
                              0 COPY_FREE_VARS           1
                
-                96           2 RESUME                   0
+                95           2 RESUME                   0
                              4 BUILD_LIST               0
                              6 LOAD_FAST                0 (.0)
                        >>    8 FOR_ITER                22 (to 54)
                
-                97          10 STORE_FAST               1 (index)
+                96          10 STORE_FAST               1 (index)
                
-                98          12 LOAD_DEREF               2 (GP)
+                97          12 LOAD_DEREF               2 (GP)
                             14 LOAD_FAST                1 (index)
                             16 BINARY_SUBSCR
                             26 LOAD_CONST               0 ('Group_Name')
                             28 BINARY_SUBSCR
                             38 LOAD_CONST               1 ('POINT')
                             40 COMPARE_OP               2 (==)
                
-                96          46 POP_JUMP_BACKWARD_IF_FALSE    20 (to 8)
+                95          46 POP_JUMP_BACKWARD_IF_FALSE    20 (to 8)
                
-                97          48 LOAD_FAST                1 (index)
+                96          48 LOAD_FAST                1 (index)
                
-                96          50 LIST_APPEND              2
+                95          50 LIST_APPEND              2
                             52 JUMP_BACKWARD           23 (to 8)
                        >>   54 RETURN_VALUE
                consts
                   'Group_Name'
                   'POINT'
                names      ()
                varnames   ('.0', 'index')
                freevars   ('GP',)
                cellvars   ()
                filename   '\\Python311\\Lib\\site-packages\\pyc3dtools\\pyc3dtools.py'
                name       '<listcomp>'
-               firstlineno 96
+               firstlineno 95
                lnotab 0x0a01020122fe020102ff
             0
             code
                argcount  : 1
                nlocals   : 2
                stacksize : 4
                flags     : 19
                code
                   0x9502970067007c005d227d018902890319000000000000000000640019
                   0000000000000000007c0119000000000000000000640119000000000000
                   00000064026b0200000000af207c0191028c235300
                              0 COPY_FREE_VARS           2
                
-               100           2 RESUME                   0
+                99           2 RESUME                   0
                              4 BUILD_LIST               0
                              6 LOAD_FAST                0 (.0)
                        >>    8 FOR_ITER                34 (to 78)
                
-               101          10 STORE_FAST               1 (index)
+               100          10 STORE_FAST               1 (index)
                
-               102          12 LOAD_DEREF               2 (GP)
+               101          12 LOAD_DEREF               2 (GP)
                             14 LOAD_DEREF               3 (gp_point_lbl_i)
                             16 BINARY_SUBSCR
                             26 LOAD_CONST               0 ('List_Parameters')
                             28 BINARY_SUBSCR
                             38 LOAD_FAST                1 (index)
                             40 BINARY_SUBSCR
                             50 LOAD_CONST               1 ('Param_Name')
                             52 BINARY_SUBSCR
                             62 LOAD_CONST               2 ('LABELS')
                             64 COMPARE_OP               2 (==)
                
-               100          70 POP_JUMP_BACKWARD_IF_FALSE    32 (to 8)
+                99          70 POP_JUMP_BACKWARD_IF_FALSE    32 (to 8)
                
-               101          72 LOAD_FAST                1 (index)
+               100          72 LOAD_FAST                1 (index)
                
-               100          74 LIST_APPEND              2
+                99          74 LIST_APPEND              2
                             76 JUMP_BACKWARD           35 (to 8)
                        >>   78 RETURN_VALUE
                consts
                   'List_Parameters'
                   'Param_Name'
                   'LABELS'
                names      ()
                varnames   ('.0', 'index')
                freevars   ('GP', 'gp_point_lbl_i')
                cellvars   ()
                filename   '\\Python311\\Lib\\site-packages\\pyc3dtools\\pyc3dtools.py'
                name       '<listcomp>'
-               firstlineno 100
+               firstlineno 99
                lnotab 0x0a0102013afe020102ff
             'List_Parameters'
             code
                argcount  : 1
                nlocals   : 2
                stacksize : 4
                flags     : 19
                code
                   0x9502970067007c005d227d018902890319000000000000000000640019
                   0000000000000000007c0119000000000000000000640119000000000000
                   00000064026b0200000000af207c0191028c235300
                              0 COPY_FREE_VARS           2
                
-               104           2 RESUME                   0
+               103           2 RESUME                   0
                              4 BUILD_LIST               0
                              6 LOAD_FAST                0 (.0)
                        >>    8 FOR_ITER                34 (to 78)
                
-               105          10 STORE_FAST               1 (index)
+               104          10 STORE_FAST               1 (index)
                
-               106          12 LOAD_DEREF               2 (GP)
+               105          12 LOAD_DEREF               2 (GP)
                             14 LOAD_DEREF               3 (gp_point_lbl_i)
                             16 BINARY_SUBSCR
                             26 LOAD_CONST               0 ('List_Parameters')
                             28 BINARY_SUBSCR
                             38 LOAD_FAST                1 (index)
                             40 BINARY_SUBSCR
                             50 LOAD_CONST               1 ('Param_Name')
                             52 BINARY_SUBSCR
                             62 LOAD_CONST               2 ('UNITS')
                             64 COMPARE_OP               2 (==)
                
-               104          70 POP_JUMP_BACKWARD_IF_FALSE    32 (to 8)
+               103          70 POP_JUMP_BACKWARD_IF_FALSE    32 (to 8)
                
-               105          72 LOAD_FAST                1 (index)
+               104          72 LOAD_FAST                1 (index)
                
-               104          74 LIST_APPEND              2
+               103          74 LIST_APPEND              2
                             76 JUMP_BACKWARD           35 (to 8)
                        >>   78 RETURN_VALUE
                consts
                   'List_Parameters'
                   'Param_Name'
                   'UNITS'
                names      ()
                varnames   ('.0', 'index')
                freevars   ('GP', 'gp_point_lbl_i')
                cellvars   ()
                filename   '\\Python311\\Lib\\site-packages\\pyc3dtools\\pyc3dtools.py'
                name       '<listcomp>'
-               firstlineno 104
+               firstlineno 103
                lnotab 0x0a0102013afe020102ff
             code
                argcount  : 1
                nlocals   : 2
                stacksize : 4
                flags     : 19
                code
                   0x9502970067007c005d227d018902890319000000000000000000640019
                   0000000000000000007c0119000000000000000000640119000000000000
                   00000064026b0200000000af207c0191028c235300
                              0 COPY_FREE_VARS           2
                
-               108           2 RESUME                   0
+               107           2 RESUME                   0
                              4 BUILD_LIST               0
                              6 LOAD_FAST                0 (.0)
                        >>    8 FOR_ITER                34 (to 78)
                
-               109          10 STORE_FAST               1 (index)
+               108          10 STORE_FAST               1 (index)
                
-               110          12 LOAD_DEREF               2 (GP)
+               109          12 LOAD_DEREF               2 (GP)
                             14 LOAD_DEREF               3 (gp_point_lbl_i)
                             16 BINARY_SUBSCR
                             26 LOAD_CONST               0 ('List_Parameters')
                             28 BINARY_SUBSCR
                             38 LOAD_FAST                1 (index)
                             40 BINARY_SUBSCR
                             50 LOAD_CONST               1 ('Param_Name')
                             52 BINARY_SUBSCR
                             62 LOAD_CONST               2 ('Y_SCREEN')
                             64 COMPARE_OP               2 (==)
                
-               108          70 POP_JUMP_BACKWARD_IF_FALSE    32 (to 8)
+               107          70 POP_JUMP_BACKWARD_IF_FALSE    32 (to 8)
                
-               109          72 LOAD_FAST                1 (index)
+               108          72 LOAD_FAST                1 (index)
                
-               108          74 LIST_APPEND              2
+               107          74 LIST_APPEND              2
                             76 JUMP_BACKWARD           35 (to 8)
                        >>   78 RETURN_VALUE
                consts
                   'List_Parameters'
                   'Param_Name'
                   'Y_SCREEN'
                names      ()
                varnames   ('.0', 'index')
                freevars   ('GP', 'gp_point_lbl_i')
                cellvars   ()
                filename   '\\Python311\\Lib\\site-packages\\pyc3dtools\\pyc3dtools.py'
                name       '<listcomp>'
-               firstlineno 108
+               firstlineno 107
                lnotab 0x0a0102013afe020102ff
             code
                argcount  : 1
                nlocals   : 2
                stacksize : 4
                flags     : 19
                code
                   0x9502970067007c005d227d018902890319000000000000000000640019
                   0000000000000000007c0119000000000000000000640119000000000000
                   00000064026b0200000000af207c0191028c235300
                              0 COPY_FREE_VARS           2
                
-               112           2 RESUME                   0
+               111           2 RESUME                   0
                              4 BUILD_LIST               0
                              6 LOAD_FAST                0 (.0)
                        >>    8 FOR_ITER                34 (to 78)
                
-               113          10 STORE_FAST               1 (index)
+               112          10 STORE_FAST               1 (index)
                
-               114          12 LOAD_DEREF               2 (GP)
+               113          12 LOAD_DEREF               2 (GP)
                             14 LOAD_DEREF               3 (gp_point_lbl_i)
                             16 BINARY_SUBSCR
                             26 LOAD_CONST               0 ('List_Parameters')
                             28 BINARY_SUBSCR
                             38 LOAD_FAST                1 (index)
                             40 BINARY_SUBSCR
                             50 LOAD_CONST               1 ('Param_Name')
                             52 BINARY_SUBSCR
                             62 LOAD_CONST               2 ('X_SCREEN')
                             64 COMPARE_OP               2 (==)
                
-               112          70 POP_JUMP_BACKWARD_IF_FALSE    32 (to 8)
+               111          70 POP_JUMP_BACKWARD_IF_FALSE    32 (to 8)
                
-               113          72 LOAD_FAST                1 (index)
+               112          72 LOAD_FAST                1 (index)
                
-               112          74 LIST_APPEND              2
+               111          74 LIST_APPEND              2
                             76 JUMP_BACKWARD           35 (to 8)
                        >>   78 RETURN_VALUE
                consts
                   'List_Parameters'
                   'Param_Name'
                   'X_SCREEN'
                names      ()
                varnames   ('.0', 'index')
                freevars   ('GP', 'gp_point_lbl_i')
                cellvars   ()
                filename   '\\Python311\\Lib\\site-packages\\pyc3dtools\\pyc3dtools.py'
                name       '<listcomp>'
-               firstlineno 112
+               firstlineno 111
                lnotab 0x0a0102013afe020102ff
             'Param_data'
             code
                argcount  : 1
                nlocals   : 2
                stacksize : 4
                flags     : 19
                code
                   0x9501970067007c005d167d0189027c0119000000000000000000640019
                   00000000000000000064016b0200000000af147c0191028c175300
                              0 COPY_FREE_VARS           1
                
-               122           2 RESUME                   0
+               121           2 RESUME                   0
                              4 BUILD_LIST               0
                              6 LOAD_FAST                0 (.0)
                        >>    8 FOR_ITER                22 (to 54)
                
-               123          10 STORE_FAST               1 (index)
+               122          10 STORE_FAST               1 (index)
                
-               124          12 LOAD_DEREF               2 (GP)
+               123          12 LOAD_DEREF               2 (GP)
                             14 LOAD_FAST                1 (index)
                             16 BINARY_SUBSCR
                             26 LOAD_CONST               0 ('Group_Name')
                             28 BINARY_SUBSCR
                             38 LOAD_CONST               1 ('ANALOG')
                             40 COMPARE_OP               2 (==)
                
-               122          46 POP_JUMP_BACKWARD_IF_FALSE    20 (to 8)
+               121          46 POP_JUMP_BACKWARD_IF_FALSE    20 (to 8)
                
-               123          48 LOAD_FAST                1 (index)
+               122          48 LOAD_FAST                1 (index)
                
-               122          50 LIST_APPEND              2
+               121          50 LIST_APPEND              2
                             52 JUMP_BACKWARD           23 (to 8)
                        >>   54 RETURN_VALUE
                consts
                   'Group_Name'
                   'ANALOG'
                names      ()
                varnames   ('.0', 'index')
                freevars   ('GP',)
                cellvars   ()
                filename   '\\Python311\\Lib\\site-packages\\pyc3dtools\\pyc3dtools.py'
                name       '<listcomp>'
-               firstlineno 122
+               firstlineno 121
                lnotab 0x0a01020122fe020102ff
             code
                argcount  : 1
                nlocals   : 2
                stacksize : 4
                flags     : 19
                code
                   0x9502970067007c005d227d018902890319000000000000000000640019
                   0000000000000000007c0119000000000000000000640119000000000000
                   00000064026b0200000000af207c0191028c235300
                              0 COPY_FREE_VARS           2
                
-               126           2 RESUME                   0
+               125           2 RESUME                   0
                              4 BUILD_LIST               0
                              6 LOAD_FAST                0 (.0)
                        >>    8 FOR_ITER                34 (to 78)
                
-               127          10 STORE_FAST               1 (index)
+               126          10 STORE_FAST               1 (index)
                
-               128          12 LOAD_DEREF               2 (GP)
+               127          12 LOAD_DEREF               2 (GP)
                             14 LOAD_DEREF               3 (gp_analog_lbl_i)
                             16 BINARY_SUBSCR
                             26 LOAD_CONST               0 ('List_Parameters')
                             28 BINARY_SUBSCR
                             38 LOAD_FAST                1 (index)
                             40 BINARY_SUBSCR
                             50 LOAD_CONST               1 ('Param_Name')
                             52 BINARY_SUBSCR
                             62 LOAD_CONST               2 ('LABELS')
                             64 COMPARE_OP               2 (==)
                
-               126          70 POP_JUMP_BACKWARD_IF_FALSE    32 (to 8)
+               125          70 POP_JUMP_BACKWARD_IF_FALSE    32 (to 8)
                
-               127          72 LOAD_FAST                1 (index)
+               126          72 LOAD_FAST                1 (index)
                
-               126          74 LIST_APPEND              2
+               125          74 LIST_APPEND              2
                             76 JUMP_BACKWARD           35 (to 8)
                        >>   78 RETURN_VALUE
                consts
                   'List_Parameters'
                   'Param_Name'
                   'LABELS'
                names      ()
                varnames   ('.0', 'index')
                freevars   ('GP', 'gp_analog_lbl_i')
                cellvars   ()
                filename   '\\Python311\\Lib\\site-packages\\pyc3dtools\\pyc3dtools.py'
                name       '<listcomp>'
-               firstlineno 126
+               firstlineno 125
                lnotab 0x0a0102013afe020102ff
             'orgin'
             'Origin'
             'COP'
             ('dtype',)
             'GRF_VECTOR'
+            1
             'Success'
             ('Status', 'GP', 'Markers', 'Points', 'Analog', 'Header', 'ForcePlate', 'Markers Label', 'Analog Label', 'Units', 'Coordinate system')
-         names      ('np', 'array', 'range', 'len', 'object')
-         varnames   ('result', 'Point', 'Real_marker_index', 'Analog', 'Header', 'Forceplates', 'Real_Markers', 'gp_point_lbl_ii', 'gp_point_unit_i', 'gp_point_Yscreen_i', 'gp_point_Xscreen_i', 'Markers_lbl', 'Markers_Units', 'Markers_YSCREEN', 'Markers_XSCREEN', 'gp_analog_lbl_ii', 'Analog_lbl', 'f')
+         names      ('np', 'array', 'range', 'len', 'object', 'int', 'append')
+         varnames   ('result', 'Point', 'Real_marker_index', 'Analog', 'Header', 'Forceplates', 'Real_Markers', 'gp_point_lbl_ii', 'gp_point_unit_i', 'gp_point_Yscreen_i', 'gp_point_Xscreen_i', 'Markers_lbl', 'Markers_Units', 'Markers_YSCREEN', 'Markers_XSCREEN', 'gp_analog_lbl_ii', 'Analog_lbl', 'f', 'NewAnalog', 'main_row', 'j', 'row', 'k')
          freevars   ()
          cellvars   ('GP', 'gp_analog_lbl_i', 'gp_point_lbl_i')
          filename   '\\Python311\\Lib\\site-packages\\pyc3dtools\\pyc3dtools.py'
          name       'GenerateOutput'
-         firstlineno 84
+         firstlineno 83
          lnotab
             0x080110011001100110011001100128011e010a03080136ff100302fd0c
             040a014eff100302fd0c040a014eff100302fd0c040a014eff100302fd0c
             040a014eff100302fd0c043401400140014003080136ff100302fd0c040a
-            014eff100302fd0c0434040801160168016a050201020102010201020102
-            01020102010201020106f5
+            014eff100302fd0c0434040801160168016a0428010401080104017c0104
+            016a0138012c022c02040402010201020102010201020102010201020102
+            0106f5
    names      ('requests', 'json', 'numpy', 'np', 'os', 'tqdm', 'tqdm.utils', 'CallbackIOWrapper', 'readC3D', 'getTRCMot', 'GenerateOutput')
    varnames   ()
    freevars   ()
    cellvars   ()
    filename   '\\Python311\\Lib\\site-packages\\pyc3dtools\\pyc3dtools.py'
    name       '<module>'
    firstlineno 1
-   lnotab 0x00ff02011001080108010c010c03061f062d
+   lnotab 0x00ff02011001080108010c010c03061d062e
```

## Comparing `Python311/Lib/site-packages/pyc3dtools-0.2.3-py3.11.egg-info/PKG-INFO` & `Python311/Lib/site-packages/pyc3dtools-0.2.4-py3.11.egg-info/PKG-INFO`

 * *Files 24% similar despite different names*

```diff
@@ -1,10 +1,10 @@
 Metadata-Version: 2.1
 Name: pyc3dtools
-Version: 0.2.3
+Version: 0.2.4
 Summary: C3Dtools API package - Read c3d files
 Home-page: https://github.com/etoshey/pyc3dtools
 Author: Soroosh.b.k (C3Dtools.com)
 Author-email: <soroosh.b.k@gmail.com>
 License: MIT
 Keywords: python,c3d,motion capture,biomechanics
 Classifier: Development Status :: 1 - Planning
@@ -103,22 +103,28 @@
 Xcop_frame_50_1 = c3d['ForcePlate'][0]['COP'][50][0][1]
 Ycop_frame_50_1 = c3d['ForcePlate'][0]['COP'][50][1][1]
 Zcop_frame_50_1 = c3d['ForcePlate'][0]['COP'][50][2][1]
 ```
 
 # Sample
 ```python
+
+import sys
 import pyc3dtools
 import matplotlib.pyplot as plt
 import numpy as np
 
-TOKEN = "YOUR_TOKEN"
+TOKEN = "eyJhbGciOiJIUzI1NiIsInR5cCI6IkpXVCJ9.eyJ1c2VySWQiOiIyNjU4NTM0NDg3NzQ2MDM0IiwiaWF0IjoxNjc5OTE4NDY1LCJleHAiOjE2Nzk5MjIwNjV9.IDZAmMoneWqw6rjlmpl15ZpjbgDjtQFhYwI_iy1uX6E"
 
 result =  pyc3dtools.readC3D(TOKEN,'TYPE-2.C3D')
 
+if result['Status']=='Failed':
+  print(f"Failed to Read File... | {result['error']}") 
+  sys.exit(0)
+
 print('---------------------------- C3Dtools.Com ----------------------------')
 print(f"Header::Number of Markers = {result['Header']['Number_of_Points']}")
 print(f"Header::First Frame = {result['Header']['first_frame']}")
 print(f"Header::Last Frame = {result['Header']['last_frame']}")
 print(f"Header::Video Sampling Rate = {result['Header']['Video_Frame_Rate']}")
 print(f"Header::Analog Channels = {result['Header']['Analog_number_channel']}")
 print(f"Header:: Analog Sample Rate = {result['Header']['Analog_Frame_Rate']}")
@@ -142,35 +148,91 @@
 print(f"First plate:: Origin = {result['ForcePlate'][0]['Origin']}")
 print(f"First plate:: COP :: X,Y,Z :: Frame->50 :: Analog Sample 1 = {result['ForcePlate'][0]['COP'][50][0][1],result['ForcePlate'][0]['COP'][50][1][1],result['ForcePlate'][0]['COP'][50][2][1]}") # Analog sample per video frame is equal 20 
 
 
 
 #plot data
 Marker1 = result['Markers'][:,1,:3]
-plt.plot(Marker1[:,0], color='r', label='X')
-plt.plot(Marker1[:,1], color='g', label='Y')
-plt.plot(Marker1[:,2], color='b', label='Z')
-plt.show()
 
 FZ = np.array(result['ForcePlate'][0]['FZ'])
 FZ = FZ.flatten()
-plt.plot(FZ)
-plt.show()
 
 
-COP = np.array(result['ForcePlate'][0]['COP'][:][:])
+COP = result['ForcePlate'][0]['COP'][:,:,:]
 COP_X = COP[:,0,:]
 COP_Y = COP[:,1,:]
 COP_X = COP_X.flatten()
 COP_Y = COP_Y.flatten()
 
 
-plt.plot(COP_X, color='g', label='copX')
-plt.plot(COP_Y, color='b', label='copY')
+Vec_GRF = result['ForcePlate'][0]['GRF_VECTOR'][:,:,:]
+Vec_GRF_X = Vec_GRF[:,0,:]
+Vec_GRF_Y = Vec_GRF[:,1,:]
+Vec_GRF_Z = Vec_GRF[:,2,:]
+Vec_GRF_X = Vec_GRF_X.flatten()
+Vec_GRF_Y = Vec_GRF_Y.flatten()
+Vec_GRF_Z = Vec_GRF_Z.flatten()
+
+
+fig = plt.figure()
+axs = fig.subplots(2, 2)
+axs[0, 0].plot(Marker1[:,0], color='r', label='X')
+axs[0, 0].plot(Marker1[:,1], color='g', label='Y')
+axs[0, 0].plot(Marker1[:,2], color='b', label='Z')
+axs[0, 0].set_title('Marker Position')
+axs[0, 1].plot(FZ, 'tab:orange')
+axs[0, 1].set_title('GRF Z')
+axs[1, 0].plot(COP_X, color='g', label='copX')
+axs[1, 0].plot(COP_Y, color='b', label='copY')
+axs[1, 0].set_title('COP')
+axs[1, 1].plot(Vec_GRF_X, color='g', label='GRFX')
+axs[1, 1].plot(Vec_GRF_Y, color='b', label='GRFY')
+axs[1, 1].plot(Vec_GRF_Z, color='r', label='GRFZ')
+axs[1, 1].set_title('GRF vector')
+
+
+
+
+NumFrames = result['Header']['last_frame'] - result['Header']['first_frame']
+
+Forceplates = result['ForcePlate']
+cop_data = []
+grf_vector = []
+corners = []
+for fp in Forceplates:  
+  #COP 
+  cop_data.append(fp['COP'])
+  #GRF
+  grf_vector.append(fp['GRF_VECTOR'])
+  #Corners
+  for c in range(4):    
+    corners.extend(fp['corners'])
+
+
+
+# COP & GRF
+main_cop_data =[]
+main_grf_data =[]
+
+for i in range(NumFrames):   
+  for fp in range(len(Forceplates)):
+    main_cop_data.append([cop_data[fp][i,0,0] , cop_data[fp][i,1,0]])
+    main_grf_data.append([grf_vector[fp][i,0,0] , grf_vector[fp][i,1,0], grf_vector[fp][i,2,0]])  
+
+
+
+# Get Analog data
+Analog_Label = result['Analog Label']
+Analog_Data = result['Analog']
+
+
 plt.show()
+
+print('OK')
+
 ```
 
 
 # Export .mot and .trc
 If you need to convert your c3d file to compatible files for OpenSim software you can use *getTRCMot* function. This function returns all c3d file data and also write .mot and .trc file in a directory
 
 ```python
```

